liberate/__init__.py
liberate/csprng/__init__.py
liberate/csprng/chacha20_cuda.cpython-311-x86_64-linux-gnu.so
liberate/csprng/chacha20_naive.py
liberate/csprng/csprng.py
liberate/csprng/discrete_gaussian_cuda.cpython-311-x86_64-linux-gnu.so
liberate/csprng/discrete_gaussian_sampler.py
liberate/csprng/randint_cuda.cpython-311-x86_64-linux-gnu.so
liberate/csprng/randround_cuda.cpython-311-x86_64-linux-gnu.so
liberate/fhe/__init__.py
liberate/fhe/cache/__init__.py
liberate/fhe/cache/cache.py
liberate/fhe/cache/resources/logN_N_M.pkl
liberate/fhe/cache/resources/message_special_primes.pkl
liberate/fhe/cache/resources/scale_primes.pkl
liberate/fhe/ckks_engine.py
liberate/fhe/context/__init__.py
liberate/fhe/context/ckks_context.py
liberate/fhe/context/generate_primes.py
liberate/fhe/context/prim_test.py
liberate/fhe/context/security_parameters.py
liberate/fhe/data_struct.py
liberate/fhe/encdec/__init__.py
liberate/fhe/encdec/encdec.py
liberate/fhe/presets/__init__.py
liberate/fhe/presets/errors.py
liberate/fhe/presets/params.py
liberate/fhe/presets/types.py
liberate/fhe/tests/test_generate_engine.py
liberate/fhe/version.py
liberate/ntt/__init__.py
liberate/ntt/ntt_context.py
liberate/ntt/ntt_cuda.cpython-311-x86_64-linux-gnu.so
liberate/ntt/rns_partition.py
liberate/utils/__init__.py
liberate/utils/helpers.py
liberate_fhe-0.9.1.dist-info/LICENSE
liberate_fhe-0.9.1.dist-info/METADATA
liberate_fhe-0.9.1.dist-info/WHEEL
liberate_fhe-0.9.1.dist-info/RECORD
