Metadata-Version: 2.1
Name: liberate-fhe
Version: 0.9.1
Summary: A Fully Homomorphic Encryption (FHE) library for bridging the gap between theory and practice with a focus on performance and accuracy
Home-page: https://desilo.ai/
License: BSD-3-Clause-Clear
Keywords: DESILO,python,cryptohraphy,privacy,encryption,cuda,homoomrphic encryption,homomorphic encryption library,fhe,gpu accelerated,liberate
Author: Juwhan Kim
Author-email: juwhan.kim@desilo.ai
Maintainer: Juwhan Kim
Maintainer-email: juwhan.kim@desilo.ai
Requires-Python: >=3.9,<3.12
Classifier: Environment :: GPU :: NVIDIA CUDA
Classifier: License :: OSI Approved :: BSD License
Classifier: License :: Other/Proprietary License
Classifier: Programming Language :: Python
Classifier: Programming Language :: Python :: 3
Classifier: Programming Language :: Python :: 3.9
Classifier: Programming Language :: Python :: 3.10
Classifier: Programming Language :: Python :: 3.11
Classifier: Topic :: Software Development :: Libraries
Requires-Dist: joblib (>=1.2.0,<2.0.0)
Requires-Dist: matplotlib (>=3.7.1,<4.0.0)
Requires-Dist: mpmath (>=1.3.0,<2.0.0)
Requires-Dist: numpy (>=1.23.5,<2.0.0)
Requires-Dist: scipy (>=1.10.1,<2.0.0)
Requires-Dist: torch (>=2.0.0,<3.0.0)
Requires-Dist: tqdm (>=4.66.1,<5.0.0)
Project-URL: Documentation, https://docs.desilo.ai/liberate-fhe/
Project-URL: Repository, https://github.com/desilo/liberate-fhe
